.DS_Store
atmosphyre/.DS_Store
atmosphyre/__init__.py
atmosphyre/dispersion.py
atmosphyre/dispersion_functions.py
atmosphyre-0.0.6.dist-info/LICENSE
atmosphyre-0.0.6.dist-info/METADATA
atmosphyre-0.0.6.dist-info/WHEEL
atmosphyre-0.0.6.dist-info/top_level.txt
atmosphyre-0.0.6.dist-info/RECORD
