Metadata-Version: 2.1
Name: atmosphyre
Version: 0.0.6
Summary: A Python package to characterise the impact of atmospheric dispersion on a spectrographs throughput.
Author: Jay Stephan
Author-email: Jay Stephan <Jay.Stephan@stfc.ac.uk>
License: MIT
License-File: LICENSE
Requires-Dist: numpy
Requires-Dist: astropy
Requires-Dist: matplotlib
Requires-Dist: scipy
